{
  "run": {
    "command": "nx deploy doc",
    "startTime": "2024-02-01T14:28:26.903Z",
    "endTime": "2024-02-01T14:29:11.867Z",
    "inner": false
  },
  "tasks": [
    {
      "taskId": "ast:build:production",
      "target": "build",
      "projectName": "ast",
      "hash": "d2a646559dbc400607bea94bc6d99bc5b552b302acc60fd376a780b065e71e2b",
      "startTime": "2024-02-01T14:28:26.908Z",
      "endTime": "2024-02-01T14:28:26.954Z",
      "params": "",
      "cacheStatus": "local-cache-hit",
      "status": 0
    },
    {
      "taskId": "core:build:production",
      "target": "build",
      "projectName": "core",
      "hash": "c449c28b23646cb3380a8602bdf6debd3f2abaa163f8c7b552558551b057fc36",
      "startTime": "2024-02-01T14:28:26.907Z",
      "endTime": "2024-02-01T14:28:26.956Z",
      "params": "",
      "cacheStatus": "local-cache-hit",
      "status": 0
    },
    {
      "taskId": "i18n:build:production",
      "target": "build",
      "projectName": "i18n",
      "hash": "c54c789706eff8aa26e85a302795f3a6c4b5040b6417afcff4c9f6999772d6aa",
      "startTime": "2024-02-01T14:28:26.908Z",
      "endTime": "2024-02-01T14:28:26.958Z",
      "params": "",
      "cacheStatus": "local-cache-hit",
      "status": 0
    },
    {
      "taskId": "icons:build:production",
      "target": "build",
      "projectName": "icons",
      "hash": "3157905a69853e016020f24e8b187ad83176f854a38def26d8e9ffdf3a722203",
      "startTime": "2024-02-01T14:28:26.956Z",
      "endTime": "2024-02-01T14:28:26.966Z",
      "params": "",
      "cacheStatus": "local-cache-hit",
      "status": 0
    },
    {
      "taskId": "helpers:build:production",
      "target": "build",
      "projectName": "helpers",
      "hash": "732625df37d800d1a60a3a2f30dbc3374f9d9fd98f187c2b390fe39a22dcc847",
      "startTime": "2024-02-01T14:28:26.956Z",
      "endTime": "2024-02-01T14:28:26.970Z",
      "params": "",
      "cacheStatus": "local-cache-hit",
      "status": 0
    },
    {
      "taskId": "flag-icons:build:production",
      "target": "build",
      "projectName": "flag-icons",
      "hash": "aab2ce5f69d4edeb74df60fbd0614268b1de84b417b0532bb178acf43b816aaf",
      "startTime": "2024-02-01T14:28:26.958Z",
      "endTime": "2024-02-01T14:28:26.972Z",
      "params": "",
      "cacheStatus": "local-cache-hit",
      "status": 0
    },
    {
      "taskId": "theme:build:production",
      "target": "build",
      "projectName": "theme",
      "hash": "14ea08d22297e4083a4a3a6c95d245772e5a3c52e1c421fae48caa7672980898",
      "startTime": "2024-02-01T14:28:26.970Z",
      "endTime": "2024-02-01T14:28:26.976Z",
      "params": "",
      "cacheStatus": "local-cache-hit",
      "status": 0
    },
    {
      "taskId": "charts-base:build:production",
      "target": "build",
      "projectName": "charts-base",
      "hash": "ca9ad0a310562814703d8afe85d8c86df3a622ac2b06708ebe0af815456939ec",
      "startTime": "2024-02-01T14:28:26.976Z",
      "endTime": "2024-02-01T14:28:26.986Z",
      "params": "",
      "cacheStatus": "local-cache-hit",
      "status": 0
    },
    {
      "taskId": "components:build:production",
      "target": "build",
      "projectName": "components",
      "hash": "16798cbf3f8484cc150ee3277e4b5ea03e4bd0d6ecf62a674d54382ea40d40bf",
      "startTime": "2024-02-01T14:28:26.976Z",
      "endTime": "2024-02-01T14:28:26.988Z",
      "params": "",
      "cacheStatus": "local-cache-hit",
      "status": 0
    },
    {
      "taskId": "doc:build:production",
      "target": "build",
      "projectName": "doc",
      "hash": "1d71b23ab5d1aeabf89c67982b94906061cc96600760ba1804aa459478aafcd7",
      "startTime": "2024-02-01T14:28:26.988Z",
      "endTime": "2024-02-01T14:28:27.063Z",
      "params": "",
      "cacheStatus": "local-cache-hit",
      "status": 0
    },
    {
      "taskId": "doc:deploy",
      "target": "deploy",
      "projectName": "doc",
      "hash": "2976760a7c7eec1d7a9ee6ccf9fd80ddebd1a17df76349aac3778b9f9def24ed",
      "startTime": "2024-02-01T14:28:27.063Z",
      "endTime": "2024-02-01T14:29:11.867Z",
      "params": "",
      "cacheStatus": "cache-miss",
      "status": 0
    }
  ]
}