{
  "0_bell-fill": 61697,
  "1_bell-plus": 61698,
  "2_bell-ring-fill": 61699,
  "3_bell-ring": 61700,
  "4_bell-slash": 61701,
  "5_bell": 61702,
  "6_check-double": 61703,
  "7_chek": 61704,
  "8_circle-chek-empty": 61705,
  "9_circle-chek-fill": 61706,
  "10_circle-exclamation-empty": 61707,
  "11_circle-exclamation-fill": 61708,
  "12_circle-info-empty": 61709,
  "13_circle-info-fill": 61710,
  "14_circle-question-empty": 61711,
  "15_circle-question-fill": 61712,
  "16_database-chek": 61713,
  "17_database-json": 61714,
  "18_database-magnifying glass": 61715,
  "19_database-minus": 61716,
  "20_database-plus": 61717,
  "21_database-sql": 61718,
  "22_database-xmark": 61719,
  "23_database": 61720,
  "24_decagram-chek-empty": 61721,
  "25_decagram-chek-fill": 61722,
  "26_decagram-exclamation-empty": 61723,
  "27_decagram-exclamation-fill": 61724,
  "28_ethernet": 61725,
  "29_exclamation": 61726,
  "30_flag-fill-red": 61727,
  "31_flag-fill": 61728,
  "32_flag": 61729,
  "33_hexagon-exclamation-empty": 61730,
  "34_hexagon-exclamation-fill": 61731,
  "35_info": 61732,
  "36_lan-connect": 61733,
  "37_lan-disconnect": 61734,
  "38_lan-pending": 61735,
  "39_network-1": 61736,
  "40_network-2": 61737,
  "41_network-3": 61738,
  "42_network-wired": 61739,
  "43_question": 61740,
  "44_server-1": 61741,
  "45_server-close": 61742,
  "46_server-download": 61743,
  "47_server-minus": 61744,
  "48_server-plus": 61745,
  "49_server-security": 61746,
  "50_server-shield": 61747,
  "51_server-slash-up-line": 61748,
  "52_server-slash": 61749,
  "53_server-up-line": 61750,
  "54_server-upload": 61751,
  "55_server": 61752,
  "56_square-exclamation-empty": 61753,
  "57_square-exclamation-fill": 61754,
  "58_square-info-empty": 61755,
  "59_square-info-fill": 61756,
  "60_square-question-empty": 61757,
  "61_square-question-fill": 61758,
  "62_triangle-cross-empty": 61759,
  "63_triangle-exclamation-empty": 61760,
  "64_triangle-exclamation-fill": 61761,
  "65_triangle-info-empty": 61762,
  "66_triangle-info-fill": 61763,
  "67_triangle-plus-empty": 61764,
  "68_user-arrows swap": 61765,
  "69_user-card": 61766,
  "70_user-check": 61767,
  "71_user-circle": 61768,
  "72_user-cross": 61769,
  "73_user-gear": 61770,
  "74_user-location": 61771,
  "75_user-minus": 61772,
  "76_user-pen": 61773,
  "77_user-plus": 61774,
  "78_user-shield": 61775,
  "79_user-worker": 61776,
  "80_user": 61777,
  "81_users-": 61778,
  "82_users-arrow right": 61779,
  "83_users-gear": 61780,
  "84_users-key": 61781,
  "85_users-location": 61782,
  "86_users-minus": 61783,
  "87_users-plus": 61784,
  "88_users": 61785
}